pyatomdb/__init__.py
pyatomdb/apec.py
pyatomdb/atomdb.py
pyatomdb/atomic.py
pyatomdb/const.py
pyatomdb/spectrum.py
pyatomdb/util.py
pyatomdb-0.0.1.5.dist-info/DESCRIPTION.rst
pyatomdb-0.0.1.5.dist-info/METADATA
pyatomdb-0.0.1.5.dist-info/RECORD
pyatomdb-0.0.1.5.dist-info/WHEEL
pyatomdb-0.0.1.5.dist-info/metadata.json
pyatomdb-0.0.1.5.dist-info/top_level.txt
