Metadata-Version: 2.0
Name: pyatomdb
Version: 0.0.1.5
Summary: AtomDB python library. This is a very early development version.
Home-page: http://www.atomdb.org
Author: Adam Foster
Author-email: afoster@cfa.harvard.edu
License: Smithsonian
Platform: UNKNOWN
Classifier: Development Status :: 2 - Pre-Alpha
Classifier: Environment :: Console
Classifier: Intended Audience :: Developers
Classifier: Intended Audience :: Education
Classifier: Intended Audience :: End Users/Desktop
Classifier: Intended Audience :: Science/Research
Classifier: Topic :: Scientific/Engineering :: Astronomy
Classifier: Topic :: Scientific/Engineering :: Physics
Classifier: Programming Language :: Python
Classifier: Operating System :: POSIX
Requires-Dist: numpy
Requires-Dist: requests
Requires-Dist: scipy
Requires-Dist: wget
